pupilio/__init__.py
pupilio/annotation.py
pupilio/callback.py
pupilio/core.py
pupilio/default_config.py
pupilio/event_detection.py
pupilio/graphics.py
pupilio/graphics_pygame.py
pupilio/misc.py
pupilio/version.py
pupilio/asset/adjust_position.wav
pupilio/asset/beep.wav
pupilio/asset/calibration_instruction.wav
pupilio/asset/dot.png
pupilio/asset/fake_face.png
pupilio/asset/figure_0.png
pupilio/asset/figure_1.png
pupilio/asset/figure_2.png
pupilio/asset/figure_3.png
pupilio/asset/figure_4.png
pupilio/asset/figure_5.png
pupilio/asset/figure_6.png
pupilio/asset/figure_7.png
pupilio/asset/figure_8.png
pupilio/asset/figure_9.png
pupilio/asset/frowning-face.png
pupilio/asset/smiling-face.png
pupilio/asset/windmill.png
pupilio/lib/DeepGazeET.dll
pupilio/lib/DummyPupilioET.dll
pupilio/lib/PupilioET.dll
pupilio-1.4.0.dist-info/LICENSE
pupilio-1.4.0.dist-info/METADATA
pupilio-1.4.0.dist-info/WHEEL
pupilio-1.4.0.dist-info/top_level.txt
pupilio-1.4.0.dist-info/RECORD
