Metadata-Version: 2.1
Name: pupilio
Version: 1.4.0
Summary: Pupilio Library
Home-page: https://github.com/GanchengZhu/Pupilio
Author: Pupilio
Author-email: zhugc2016@gmail.com
License-File: LICENSE
Requires-Dist: numpy
Requires-Dist: pygame
Requires-Dist: websockets
Requires-Dist: opencv-python
